pamagent-0.3.0.dist-info/WHEEL
pamagent-0.3.0.dist-info/RECORD
pamagent-0.3.0.dist-info/METADATA
pamagent-0.3.0.dist-info/top_level.txt
pamagent/pamagent_core.cpython-36m-i386-linux-gnu.so
pamagent/transaction_cache.py
pamagent/web_transaction.py
pamagent/agent.py
pamagent/wrapper.py
pamagent/transaction.py
pamagent/trace.py
pamagent/__init__.py
pamagent/utils/sql_statement.py
pamagent/utils/__init__.py
pamagent/hooks/dbapi2.py
pamagent/hooks/psycopg2_hook.py
pamagent/hooks/requests_hook.py
pamagent/hooks/redis_hook.py
pamagent/hooks/sqlite_hook.py
pamagent/hooks/django_hook.py
pamagent/hooks/mysql_hook.py
pamagent/hooks/__init__.py
pamagent/.libs/libssl-4a0b87e2.so.1.1
pamagent/.libs/libcrypto-f01c296d.so.1.1
