Metadata-Version: 1.2
Name: pamagent
Version: 0.3.0
Summary: Agent for PAM
Home-page: https://github.com/pushamp/pamagent
Author: PushAMP LLC
Author-email: devcore@pushamp.com
License: MIT
Keywords: pam,rust,profiling,performance
Platform: Posix; MacOS X; Windows
Classifier: Development Status :: 4 - Beta
Classifier: Intended Audience :: Developers
Classifier: License :: OSI Approved :: MIT License
Classifier: Operating System :: OS Independent
Classifier: Programming Language :: Python :: 3.5
Classifier: Programming Language :: Python :: 3.6
Classifier: Programming Language :: Python :: 3 :: Only
Requires-Python: >=3.5
